discord/ext/ipcx/__init__.py
discord/ext/ipcx/client.py
discord/ext/ipcx/errors.py
discord/ext/ipcx/py.typed
discord/ext/ipcx/server.py
discord_ext_ipcx-0.4.0.dist-info/LICENSE
discord_ext_ipcx-0.4.0.dist-info/METADATA
discord_ext_ipcx-0.4.0.dist-info/WHEEL
discord_ext_ipcx-0.4.0.dist-info/top_level.txt
discord_ext_ipcx-0.4.0.dist-info/RECORD
