Metadata-Version: 2.1
Name: discord-ext-ipcx
Version: 0.4.0
Summary: Maintained and updated version of discord-ext-ipc for discord.py v2
Author-email: No767 <73260931+No767@users.noreply.github.com>
Maintainer-email: No767 <73260931+No767@users.noreply.github.com>
Project-URL: Homepage, https://github.com/No767/discord-ext-ipcx
Project-URL: Documentation, https://discord-ext-ipcx.readthedocs.io/en/stable/
Project-URL: Repository, https://github.com/No767/discord-ext-ipcx
Project-URL: Issues, https://github.com/No767/discord-ext-ipcx/issues
Keywords: discord.py,asyncio,networking,discord-ext-ipcx,discord-ext-ipc
Classifier: Development Status :: 4 - Beta
Classifier: Framework :: AsyncIO
Classifier: Intended Audience :: Developers
Classifier: License :: OSI Approved :: Apache Software License
Classifier: Natural Language :: English
Classifier: Operating System :: OS Independent
Classifier: Programming Language :: Python :: 3.9
Classifier: Programming Language :: Python :: 3.10
Classifier: Programming Language :: Python :: 3.11
Classifier: Programming Language :: Python :: 3.12
Classifier: Programming Language :: Python :: 3.13
Classifier: Programming Language :: Python :: Implementation :: CPython
Classifier: Topic :: Internet
Classifier: Topic :: Software Development :: Libraries
Classifier: Topic :: Software Development :: Libraries :: Python Modules
Classifier: Topic :: Utilities
Classifier: Typing :: Typed
Requires-Python: <4,>=3.9
License-File: LICENSE
Requires-Dist: discord.py<3,>=2
Provides-Extra: docs
Requires-Dist: sphinx<9,>=8.1.3; extra == "docs"
Requires-Dist: sphinx-autobuild<2025,>=2024.10.3; extra == "docs"
Requires-Dist: furo<2025,>=2024.8.6; extra == "docs"
Requires-Dist: sphinx-copybutton<1,>=0.5.2; extra == "docs"
Provides-Extra: dev
Requires-Dist: lefthook<2,>=1.8.1; extra == "dev"
Requires-Dist: pyright<2,>=1.1.386; extra == "dev"
Requires-Dist: ruff<1,>=0.7.1; extra == "dev"
Requires-Dist: tox<5,>=4.23.2; extra == "dev"
Requires-Dist: towncrier<25,>=24.8.0; extra == "dev"
Provides-Extra: examples
Requires-Dist: quart<1,>=0.19.8; extra == "examples"
Requires-Dist: fastapi[standard]<1,>=0.115.6; extra == "examples"
Provides-Extra: build
Requires-Dist: build<2,>=1.2.2.post1; extra == "build"
